{
  "id": "evil_0867",
  "puzzle": "090000700050480900462000000000714020210050000070920056000206040807000603000800015",
  "solution": "198562734753481962462379581685714329219653478374928156531296847827145693946837215",
  "difficulty": "evil",
  "clues": 31,
  "fill_percent": 38.3,
  "symmetry": "random",
  "techniques": [
    "LastBlank",
    "FullHouse",
    "NakedSingle",
    "HiddenSingle",
    "PointingPair",
    "PointingTriple",
    "BoxLineReduction",
    "NakedPair",
    "HiddenPair",
    "NakedTriple",
    "HiddenTriple",
    "NakedQuad",
    "HiddenQuad",
    "XWing",
    "XYWing",
    "XYZWing",
    "WWing",
    "Swordfish",
    "Jellyfish",
    "WXYZWing",
    "VWXYZWing",
    "UniqueRectangle",
    "HiddenRectangle",
    "AvoidableRectangle",
    "ExtendedRectangle",
    "BUG+1",
    "BUG+2",
    "QWing",
    "EmptyRectangle",
    "FinnedXWing",
    "FinnedSwordfish",
    "SashimiXWing",
    "SashimiSwordfish"
  ],
  "steps": 50,
  "hash": "a90344e83c0e052f",
  "checksum": "a90344e83c0e052f",
  "human_score": 7,
  "visual_score": 0.383,
  "tier_max": 7,
  "estimated_time_minutes": 30,
  "tramo": 801,
  "level_index": 867,
  "difficulty_label": "Evil"
}