{
  "id": "evil_0503",
  "puzzle": "908163705035040260000802000086917520007000100200506007810000053002000800000000000",
  "solution": "928163745135749268674852319386917524597428136241536987819274653462395871753681492",
  "difficulty": "evil",
  "clues": 33,
  "fill_percent": 40.7,
  "symmetry": "mirror",
  "techniques": [
    "LastBlank",
    "FullHouse",
    "NakedSingle",
    "HiddenSingle",
    "PointingPair",
    "PointingTriple",
    "BoxLineReduction",
    "NakedPair",
    "HiddenPair",
    "NakedTriple",
    "HiddenTriple",
    "NakedQuad",
    "HiddenQuad",
    "XWing",
    "XYWing",
    "XYZWing",
    "WWing",
    "Swordfish",
    "Jellyfish",
    "WXYZWing",
    "VWXYZWing",
    "UniqueRectangle",
    "HiddenRectangle",
    "AvoidableRectangle",
    "ExtendedRectangle"
  ],
  "steps": 48,
  "hash": "00d1f4aabf073753",
  "checksum": "00d1f4aabf073753",
  "human_score": 5,
  "visual_score": 0.407,
  "tier_max": 5,
  "estimated_time_minutes": 20,
  "tramo": 401,
  "level_index": 503,
  "difficulty_label": "Evil"
}