{
  "id": "evil_0191",
  "puzzle": "015690000003751698007200105000100000008060019000382507100070830000013006030820070",
  "solution": "815694723243751698967238145576149382328567419491382567152976834789413256634825971",
  "difficulty": "evil",
  "clues": 36,
  "fill_percent": 44.4,
  "symmetry": "random",
  "techniques": [
    "LastBlank",
    "FullHouse",
    "NakedSingle",
    "HiddenSingle",
    "PointingPair",
    "PointingTriple",
    "BoxLineReduction",
    "NakedPair",
    "HiddenPair",
    "NakedTriple",
    "HiddenTriple",
    "NakedQuad",
    "HiddenQuad",
    "XWing",
    "XYWing",
    "XYZWing",
    "WWing",
    "Swordfish"
  ],
  "steps": 45,
  "hash": "bbb720e03fc1b7c9",
  "checksum": "bbb720e03fc1b7c9",
  "human_score": 5,
  "visual_score": 0.444,
  "tier_max": 5,
  "estimated_time_minutes": 15,
  "tramo": 1,
  "level_index": 191,
  "difficulty_label": "Evil"
}