{
  "id": "evil_0668",
  "puzzle": "060200538009105470000034900000980060078002000903601050500010009840500000000400080",
  "solution": "164279538389165472257834916415987263678352194923641857532718649846593721791426385",
  "difficulty": "evil",
  "clues": 32,
  "fill_percent": 39.5,
  "symmetry": "random",
  "techniques": [
    "LastBlank",
    "FullHouse",
    "NakedSingle",
    "HiddenSingle",
    "PointingPair",
    "PointingTriple",
    "BoxLineReduction",
    "NakedPair",
    "HiddenPair",
    "NakedTriple",
    "HiddenTriple",
    "NakedQuad",
    "HiddenQuad",
    "XWing",
    "XYWing",
    "XYZWing",
    "WWing",
    "Swordfish",
    "Jellyfish",
    "WXYZWing",
    "VWXYZWing",
    "UniqueRectangle",
    "HiddenRectangle",
    "AvoidableRectangle",
    "ExtendedRectangle",
    "BUG+1",
    "BUG+2",
    "QWing",
    "EmptyRectangle"
  ],
  "steps": 49,
  "hash": "436508214d866d1b",
  "checksum": "436508214d866d1b",
  "human_score": 6,
  "visual_score": 0.395,
  "tier_max": 6,
  "estimated_time_minutes": 25,
  "tramo": 601,
  "level_index": 668,
  "difficulty_label": "Evil"
}