{
  "id": "evil_0924",
  "puzzle": "360000050900010040051000900079000060000640000040897013507080000012704005090300000",
  "solution": "364978152928513647751426938179235864283641579645897213537189426812764395496352781",
  "difficulty": "evil",
  "clues": 30,
  "fill_percent": 37.0,
  "symmetry": "random",
  "techniques": [
    "LastBlank",
    "FullHouse",
    "NakedSingle",
    "HiddenSingle",
    "PointingPair",
    "PointingTriple",
    "BoxLineReduction",
    "NakedPair",
    "HiddenPair",
    "NakedTriple",
    "HiddenTriple",
    "NakedQuad",
    "HiddenQuad",
    "XWing",
    "XYWing",
    "XYZWing",
    "WWing",
    "Swordfish",
    "Jellyfish",
    "WXYZWing",
    "VWXYZWing",
    "UniqueRectangle",
    "HiddenRectangle",
    "AvoidableRectangle",
    "ExtendedRectangle",
    "BUG+1",
    "BUG+2",
    "QWing",
    "EmptyRectangle",
    "FinnedXWing",
    "FinnedSwordfish",
    "SashimiXWing",
    "SashimiSwordfish"
  ],
  "steps": 51,
  "hash": "2f8f945f4f21e7f8",
  "checksum": "2f8f945f4f21e7f8",
  "human_score": 7,
  "visual_score": 0.37,
  "tier_max": 7,
  "estimated_time_minutes": 30,
  "tramo": 801,
  "level_index": 924,
  "difficulty_label": "Evil"
}