{
  "id": "evil_0007",
  "puzzle": "000470020480002000276000080063009750942000000007046030690080200504100009028965001",
  "solution": "319478526485632197276591483863219754942753618157846932691384275534127869728965341",
  "difficulty": "evil",
  "clues": 36,
  "fill_percent": 44.4,
  "symmetry": "random",
  "techniques": [
    "LastBlank",
    "FullHouse",
    "NakedSingle",
    "HiddenSingle",
    "PointingPair",
    "PointingTriple",
    "BoxLineReduction",
    "NakedPair",
    "HiddenPair",
    "NakedTriple",
    "HiddenTriple",
    "NakedQuad",
    "HiddenQuad",
    "XWing",
    "XYWing",
    "XYZWing",
    "WWing",
    "Swordfish"
  ],
  "steps": 45,
  "hash": "5b008e7abfe0d1e2",
  "checksum": "5b008e7abfe0d1e2",
  "human_score": 5,
  "visual_score": 0.444,
  "tier_max": 5,
  "estimated_time_minutes": 15,
  "tramo": 1,
  "level_index": 7,
  "difficulty_label": "Evil"
}