{
  "id": "evil_0842",
  "puzzle": "000008693000000000000340210064509800709030504001804960097083000000000000342100000",
  "solution": "425718693813962475976345218264579831789631524531824967697483152158297346342156789",
  "difficulty": "evil",
  "clues": 31,
  "fill_percent": 38.3,
  "symmetry": "rotational",
  "techniques": [
    "LastBlank",
    "FullHouse",
    "NakedSingle",
    "HiddenSingle",
    "PointingPair",
    "PointingTriple",
    "BoxLineReduction",
    "NakedPair",
    "HiddenPair",
    "NakedTriple",
    "HiddenTriple",
    "NakedQuad",
    "HiddenQuad",
    "XWing",
    "XYWing",
    "XYZWing",
    "WWing",
    "Swordfish",
    "Jellyfish",
    "WXYZWing",
    "VWXYZWing",
    "UniqueRectangle",
    "HiddenRectangle",
    "AvoidableRectangle",
    "ExtendedRectangle",
    "BUG+1",
    "BUG+2",
    "QWing",
    "EmptyRectangle",
    "FinnedXWing",
    "FinnedSwordfish",
    "SashimiXWing",
    "SashimiSwordfish"
  ],
  "steps": 50,
  "hash": "725d2adf27c6f563",
  "checksum": "725d2adf27c6f563",
  "human_score": 7,
  "visual_score": 0.383,
  "tier_max": 7,
  "estimated_time_minutes": 30,
  "tramo": 801,
  "level_index": 842,
  "difficulty_label": "Evil"
}