{
  "id": "evil_0864",
  "puzzle": "030901402007003000109702000060800090000007001308059004070200000046005209000008107",
  "solution": "635981472427563918189742356762814593594327681318659724971236845846175239253498167",
  "difficulty": "evil",
  "clues": 31,
  "fill_percent": 38.3,
  "symmetry": "random",
  "techniques": [
    "LastBlank",
    "FullHouse",
    "NakedSingle",
    "HiddenSingle",
    "PointingPair",
    "PointingTriple",
    "BoxLineReduction",
    "NakedPair",
    "HiddenPair",
    "NakedTriple",
    "HiddenTriple",
    "NakedQuad",
    "HiddenQuad",
    "XWing",
    "XYWing",
    "XYZWing",
    "WWing",
    "Swordfish",
    "Jellyfish",
    "WXYZWing",
    "VWXYZWing",
    "UniqueRectangle",
    "HiddenRectangle",
    "AvoidableRectangle",
    "ExtendedRectangle",
    "BUG+1",
    "BUG+2",
    "QWing",
    "EmptyRectangle",
    "FinnedXWing",
    "FinnedSwordfish",
    "SashimiXWing",
    "SashimiSwordfish"
  ],
  "steps": 50,
  "hash": "beed155f5cc44bf6",
  "checksum": "beed155f5cc44bf6",
  "human_score": 7,
  "visual_score": 0.383,
  "tier_max": 7,
  "estimated_time_minutes": 30,
  "tramo": 801,
  "level_index": 864,
  "difficulty_label": "Evil"
}