{
  "id": "evil_0154",
  "puzzle": "304507019108042000072061000830000000000000508006010073500006032020058700480723006",
  "solution": "364587219158942367972361485835279641791634528246815973517496832623158794489723156",
  "difficulty": "evil",
  "clues": 36,
  "fill_percent": 44.4,
  "symmetry": "random",
  "techniques": [
    "LastBlank",
    "FullHouse",
    "NakedSingle",
    "HiddenSingle",
    "PointingPair",
    "PointingTriple",
    "BoxLineReduction",
    "NakedPair",
    "HiddenPair",
    "NakedTriple",
    "HiddenTriple",
    "NakedQuad",
    "HiddenQuad",
    "XWing",
    "XYWing",
    "XYZWing",
    "WWing",
    "Swordfish"
  ],
  "steps": 45,
  "hash": "5b9c950815612957",
  "checksum": "5b9c950815612957",
  "human_score": 5,
  "visual_score": 0.444,
  "tier_max": 5,
  "estimated_time_minutes": 15,
  "tramo": 1,
  "level_index": 154,
  "difficulty_label": "Evil"
}