{
  "id": "evil_0185",
  "puzzle": "204609000086004971037001040620000039000000000190000027070400610469700350000206704",
  "solution": "214679583586324971937851246625147839743982165198563427372495618469718352851236794",
  "difficulty": "evil",
  "clues": 36,
  "fill_percent": 44.4,
  "symmetry": "rotational",
  "techniques": [
    "LastBlank",
    "FullHouse",
    "NakedSingle",
    "HiddenSingle",
    "PointingPair",
    "PointingTriple",
    "BoxLineReduction",
    "NakedPair",
    "HiddenPair",
    "NakedTriple",
    "HiddenTriple",
    "NakedQuad",
    "HiddenQuad",
    "XWing",
    "XYWing",
    "XYZWing",
    "WWing",
    "Swordfish"
  ],
  "steps": 45,
  "hash": "6e529f8b2e8e8775",
  "checksum": "6e529f8b2e8e8775",
  "human_score": 5,
  "visual_score": 0.444,
  "tier_max": 5,
  "estimated_time_minutes": 15,
  "tramo": 1,
  "level_index": 185,
  "difficulty_label": "Evil"
}