{
  "id": "evil_0618",
  "puzzle": "072106390400873005080000060000080000600000002814000756703010509000000000005269800",
  "solution": "572146398496873215381925467257681934639754182814392756763418529928537641145269873",
  "difficulty": "evil",
  "clues": 32,
  "fill_percent": 39.5,
  "symmetry": "mirror",
  "techniques": [
    "LastBlank",
    "FullHouse",
    "NakedSingle",
    "HiddenSingle",
    "PointingPair",
    "PointingTriple",
    "BoxLineReduction",
    "NakedPair",
    "HiddenPair",
    "NakedTriple",
    "HiddenTriple",
    "NakedQuad",
    "HiddenQuad",
    "XWing",
    "XYWing",
    "XYZWing",
    "WWing",
    "Swordfish",
    "Jellyfish",
    "WXYZWing",
    "VWXYZWing",
    "UniqueRectangle",
    "HiddenRectangle",
    "AvoidableRectangle",
    "ExtendedRectangle",
    "BUG+1",
    "BUG+2",
    "QWing",
    "EmptyRectangle"
  ],
  "steps": 49,
  "hash": "28c1fbc336ad6a0a",
  "checksum": "28c1fbc336ad6a0a",
  "human_score": 6,
  "visual_score": 0.395,
  "tier_max": 6,
  "estimated_time_minutes": 25,
  "tramo": 601,
  "level_index": 618,
  "difficulty_label": "Evil"
}