{
  "id": "evil_0031",
  "puzzle": "008000700070080030905020608093204860520000014846307925080040070002000100000163000",
  "solution": "218436759674589231935721648193254867527698314846317925381942576462875193759163482",
  "difficulty": "evil",
  "clues": 36,
  "fill_percent": 44.4,
  "symmetry": "mirror",
  "techniques": [
    "LastBlank",
    "FullHouse",
    "NakedSingle",
    "HiddenSingle",
    "PointingPair",
    "PointingTriple",
    "BoxLineReduction",
    "NakedPair",
    "HiddenPair",
    "NakedTriple",
    "HiddenTriple",
    "NakedQuad",
    "HiddenQuad",
    "XWing",
    "XYWing",
    "XYZWing",
    "WWing",
    "Swordfish"
  ],
  "steps": 45,
  "hash": "df5234b42b9cb6ce",
  "checksum": "df5234b42b9cb6ce",
  "human_score": 5,
  "visual_score": 0.444,
  "tier_max": 5,
  "estimated_time_minutes": 15,
  "tramo": 1,
  "level_index": 31,
  "difficulty_label": "Evil"
}