{
  "id": "evil_0979",
  "puzzle": "008000095000010000570042601027000008040093200060204910090007100000001000100400760",
  "solution": "218376495634519872579842631927165348841793256365284917492657183786931524153428769",
  "difficulty": "evil",
  "clues": 30,
  "fill_percent": 37.0,
  "symmetry": "random",
  "techniques": [
    "LastBlank",
    "FullHouse",
    "NakedSingle",
    "HiddenSingle",
    "PointingPair",
    "PointingTriple",
    "BoxLineReduction",
    "NakedPair",
    "HiddenPair",
    "NakedTriple",
    "HiddenTriple",
    "NakedQuad",
    "HiddenQuad",
    "XWing",
    "XYWing",
    "XYZWing",
    "WWing",
    "Swordfish",
    "Jellyfish",
    "WXYZWing",
    "VWXYZWing",
    "UniqueRectangle",
    "HiddenRectangle",
    "AvoidableRectangle",
    "ExtendedRectangle",
    "BUG+1",
    "BUG+2",
    "QWing",
    "EmptyRectangle",
    "FinnedXWing",
    "FinnedSwordfish",
    "SashimiXWing",
    "SashimiSwordfish"
  ],
  "steps": 51,
  "hash": "84c6268577773072",
  "checksum": "84c6268577773072",
  "human_score": 7,
  "visual_score": 0.37,
  "tier_max": 7,
  "estimated_time_minutes": 30,
  "tramo": 801,
  "level_index": 979,
  "difficulty_label": "Evil"
}