{
  "id": "evil_0620",
  "puzzle": "504071030001000000008900076050302004736480000400000000000006920090020010247105300",
  "solution": "564271839971638542328954176159362784736489251482517693813746925695823417247195368",
  "difficulty": "evil",
  "clues": 32,
  "fill_percent": 39.5,
  "symmetry": "random",
  "techniques": [
    "LastBlank",
    "FullHouse",
    "NakedSingle",
    "HiddenSingle",
    "PointingPair",
    "PointingTriple",
    "BoxLineReduction",
    "NakedPair",
    "HiddenPair",
    "NakedTriple",
    "HiddenTriple",
    "NakedQuad",
    "HiddenQuad",
    "XWing",
    "XYWing",
    "XYZWing",
    "WWing",
    "Swordfish",
    "Jellyfish",
    "WXYZWing",
    "VWXYZWing",
    "UniqueRectangle",
    "HiddenRectangle",
    "AvoidableRectangle",
    "ExtendedRectangle",
    "BUG+1",
    "BUG+2",
    "QWing",
    "EmptyRectangle"
  ],
  "steps": 49,
  "hash": "18da30e1ecce5782",
  "checksum": "18da30e1ecce5782",
  "human_score": 6,
  "visual_score": 0.395,
  "tier_max": 6,
  "estimated_time_minutes": 25,
  "tramo": 601,
  "level_index": 620,
  "difficulty_label": "Evil"
}