{
  "id": "evil_0319",
  "puzzle": "000960000985000000120700009039007005060015900851003026000549302500000000004206091",
  "solution": "743962158985134267126758439439627815267815943851493726618549372592371684374286591",
  "difficulty": "evil",
  "clues": 34,
  "fill_percent": 42.0,
  "symmetry": "random",
  "techniques": [
    "LastBlank",
    "FullHouse",
    "NakedSingle",
    "HiddenSingle",
    "PointingPair",
    "PointingTriple",
    "BoxLineReduction",
    "NakedPair",
    "HiddenPair",
    "NakedTriple",
    "HiddenTriple",
    "NakedQuad",
    "HiddenQuad",
    "XWing",
    "XYWing",
    "XYZWing",
    "WWing",
    "Swordfish",
    "Jellyfish",
    "WXYZWing",
    "VWXYZWing"
  ],
  "steps": 47,
  "hash": "9e0b3c1f95e6a772",
  "checksum": "9e0b3c1f95e6a772",
  "human_score": 5,
  "visual_score": 0.42,
  "tier_max": 5,
  "estimated_time_minutes": 18,
  "tramo": 201,
  "level_index": 319,
  "difficulty_label": "Evil"
}