{
  "id": "mythic_0386",
  "puzzle": "040000010100030007900000006500804009004165800010000070050403020007000500200090004",
  "solution": "342756918165938247978241356523874169794165832816329475659483721487612593231597684",
  "difficulty": "mythic",
  "clues": 27,
  "fill_percent": 33.3,
  "symmetry": "mirror",
  "techniques": [
    "AIC",
    "AvoidableRectangle",
    "BoxLineReduction",
    "BUG+1",
    "BUG+2",
    "EmptyRectangle",
    "ExtendedRectangle",
    "FinnedSwordfish",
    "FinnedXWing",
    "FullHouse",
    "HiddenPair",
    "HiddenQuad",
    "HiddenRectangle",
    "HiddenSingle",
    "HiddenTriple",
    "Jellyfish",
    "LastBlank",
    "NakedPair",
    "NakedQuad",
    "NakedSingle",
    "NakedTriple",
    "PointingPair",
    "PointingTriple",
    "QWing",
    "RemotePairs",
    "SashimiFish",
    "SimpleColoring",
    "Swordfish",
    "UniqueRectangle",
    "VWXYZWing",
    "WWing",
    "WXYZWing",
    "XCycle",
    "XWing",
    "XYChain",
    "XYWing",
    "XYZWing"
  ],
  "steps": 54,
  "hash": "abb5c4058edd2452",
  "checksum": "abb5c4058edd2452",
  "human_score": 5,
  "visual_score": 0.333,
  "tier_max": 5,
  "estimated_time_minutes": 45,
  "tramo": 301,
  "level_index": 386,
  "difficulty_label": "Mythic"
}