{
  "id": "mythic_0332",
  "puzzle": "002000090000023000000004600000082000009005427000400058004518200650090304080000000",
  "solution": "342671895596823741178954632415782963869135427723469158934518276651297384287346519",
  "difficulty": "mythic",
  "clues": 27,
  "fill_percent": 33.3,
  "symmetry": "random",
  "techniques": [
    "AIC",
    "AvoidableRectangle",
    "BoxLineReduction",
    "BUG+1",
    "BUG+2",
    "EmptyRectangle",
    "ExtendedRectangle",
    "FinnedSwordfish",
    "FinnedXWing",
    "FullHouse",
    "HiddenPair",
    "HiddenQuad",
    "HiddenRectangle",
    "HiddenSingle",
    "HiddenTriple",
    "Jellyfish",
    "LastBlank",
    "NakedPair",
    "NakedQuad",
    "NakedSingle",
    "NakedTriple",
    "PointingPair",
    "PointingTriple",
    "QWing",
    "RemotePairs",
    "SashimiFish",
    "SimpleColoring",
    "Swordfish",
    "UniqueRectangle",
    "VWXYZWing",
    "WWing",
    "WXYZWing",
    "XCycle",
    "XWing",
    "XYChain",
    "XYWing",
    "XYZWing"
  ],
  "steps": 54,
  "hash": "ee4a1e6dcd96c7e9",
  "checksum": "ee4a1e6dcd96c7e9",
  "human_score": 5,
  "visual_score": 0.333,
  "tier_max": 5,
  "estimated_time_minutes": 45,
  "tramo": 301,
  "level_index": 332,
  "difficulty_label": "Mythic"
}