{
  "id": "hard_0818",
  "puzzle": "720095001051200890849010023007039080205468109090170300510020738084001960900380015",
  "solution": "723895641651243897849617523167539284235468179498172356516924738384751962972386415",
  "difficulty": "hard",
  "clues": 47,
  "fill_percent": 58.0,
  "symmetry": "rotational",
  "techniques": [
    "LastBlank",
    "FullHouse",
    "NakedSingle",
    "HiddenSingle",
    "PointingPair",
    "PointingTriple",
    "BoxLineReduction",
    "NakedPair",
    "HiddenPair",
    "NakedTriple",
    "HiddenTriple",
    "NakedQuad",
    "HiddenQuad"
  ],
  "steps": 34,
  "hash": "42e9f804659ffda1",
  "checksum": "42e9f804659ffda1",
  "human_score": 4,
  "visual_score": 0.58,
  "tier_max": 4,
  "estimated_time_minutes": 8,
  "tramo": 651,
  "level_index": 818,
  "difficulty_label": "Hard"
}