{
  "id": "hard_0848",
  "puzzle": "872000403405729001900080007207065138006234900359870206600040002700318609503000784",
  "solution": "872156493435729861961483527247965138186234975359871246698547312724318659513692784",
  "difficulty": "hard",
  "clues": 47,
  "fill_percent": 58.0,
  "symmetry": "rotational",
  "techniques": [
    "LastBlank",
    "FullHouse",
    "NakedSingle",
    "HiddenSingle",
    "PointingPair",
    "PointingTriple",
    "BoxLineReduction",
    "NakedPair",
    "HiddenPair",
    "NakedTriple",
    "HiddenTriple",
    "NakedQuad",
    "HiddenQuad"
  ],
  "steps": 34,
  "hash": "06e88f647f6be54e",
  "checksum": "06e88f647f6be54e",
  "human_score": 4,
  "visual_score": 0.58,
  "tier_max": 4,
  "estimated_time_minutes": 8,
  "tramo": 651,
  "level_index": 848,
  "difficulty_label": "Hard"
}