{
  "id": "expert_0953",
  "puzzle": "008030401900810326023640080200100060000000900060402013830024650090051038500006100",
  "solution": "658237491947815326123649785289173564314568972765492813831924657496751238572386149",
  "difficulty": "expert",
  "clues": 38,
  "fill_percent": 46.9,
  "symmetry": "random",
  "techniques": [
    "LastBlank",
    "FullHouse",
    "NakedSingle",
    "HiddenSingle",
    "PointingPair",
    "PointingTriple",
    "BoxLineReduction",
    "NakedPair",
    "HiddenPair",
    "NakedTriple",
    "HiddenTriple",
    "NakedQuad",
    "HiddenQuad",
    "XWing",
    "XYWing",
    "XYZWing",
    "WWing",
    "Swordfish",
    "Jellyfish",
    "WXYZWing"
  ],
  "steps": 43,
  "hash": "6f2935bb5f6b1004",
  "checksum": "6f2935bb5f6b1004",
  "human_score": 5,
  "visual_score": 0.469,
  "tier_max": 5,
  "estimated_time_minutes": 14,
  "tramo": 801,
  "level_index": 953,
  "difficulty_label": "Expert"
}