{
  "id": "expert_0270",
  "puzzle": "268009070140067050350802906900070020080601090070020004704106039090780062030200715",
  "solution": "268549371149367258357812946915478623482631597673925184724156839591783462836294715",
  "difficulty": "expert",
  "clues": 42,
  "fill_percent": 51.9,
  "symmetry": "rotational",
  "techniques": [
    "LastBlank",
    "FullHouse",
    "NakedSingle",
    "HiddenSingle",
    "PointingPair",
    "PointingTriple",
    "BoxLineReduction",
    "NakedPair",
    "HiddenPair",
    "NakedTriple",
    "HiddenTriple",
    "NakedQuad",
    "HiddenQuad",
    "XWing",
    "XYWing"
  ],
  "steps": 39,
  "hash": "03a3534405b4edb3",
  "checksum": "03a3534405b4edb3",
  "human_score": 4,
  "visual_score": 0.519,
  "tier_max": 4,
  "estimated_time_minutes": 9,
  "tramo": 201,
  "level_index": 270,
  "difficulty_label": "Expert"
}