{
  "id": "expert_0714",
  "puzzle": "003400750508029160007005409002940001400107002600038900206800300014570806085003200",
  "solution": "923461758548729163167385429872946531439157682651238947296814375314572896785693214",
  "difficulty": "expert",
  "clues": 40,
  "fill_percent": 49.4,
  "symmetry": "rotational",
  "techniques": [
    "LastBlank",
    "FullHouse",
    "NakedSingle",
    "HiddenSingle",
    "PointingPair",
    "PointingTriple",
    "BoxLineReduction",
    "NakedPair",
    "HiddenPair",
    "NakedTriple",
    "HiddenTriple",
    "NakedQuad",
    "HiddenQuad",
    "XWing",
    "XYWing",
    "XYZWing",
    "WWing",
    "Swordfish"
  ],
  "steps": 41,
  "hash": "a8f3765189c88dce",
  "checksum": "a8f3765189c88dce",
  "human_score": 5,
  "visual_score": 0.494,
  "tier_max": 5,
  "estimated_time_minutes": 12,
  "tramo": 601,
  "level_index": 714,
  "difficulty_label": "Expert"
}