{
  "id": "expert_0549",
  "puzzle": "000309000480126053306000109802000905630907082094080670100090004903060507057030890",
  "solution": "715349268489126753326578149872614935631957482594283671168795324943862517257431896",
  "difficulty": "expert",
  "clues": 41,
  "fill_percent": 50.6,
  "symmetry": "mirror",
  "techniques": [
    "LastBlank",
    "FullHouse",
    "NakedSingle",
    "HiddenSingle",
    "PointingPair",
    "PointingTriple",
    "BoxLineReduction",
    "NakedPair",
    "HiddenPair",
    "NakedTriple",
    "HiddenTriple",
    "NakedQuad",
    "HiddenQuad",
    "XWing",
    "XYWing",
    "XYZWing",
    "WWing"
  ],
  "steps": 40,
  "hash": "269ac3b06e20f934",
  "checksum": "269ac3b06e20f934",
  "human_score": 4,
  "visual_score": 0.506,
  "tier_max": 4,
  "estimated_time_minutes": 10,
  "tramo": 401,
  "level_index": 549,
  "difficulty_label": "Expert"
}