{
  "id": "expert_0169",
  "puzzle": "050060900902480317007391526009506003725900860004810050003000478000074030406208105",
  "solution": "351762984962485317847391526189526743725943861634817259213659478598174632476238195",
  "difficulty": "expert",
  "clues": 44,
  "fill_percent": 54.3,
  "symmetry": "random",
  "techniques": [
    "LastBlank",
    "FullHouse",
    "NakedSingle",
    "HiddenSingle",
    "PointingPair",
    "PointingTriple",
    "BoxLineReduction",
    "NakedPair",
    "HiddenPair",
    "NakedTriple",
    "HiddenTriple",
    "NakedQuad",
    "HiddenQuad",
    "XWing"
  ],
  "steps": 37,
  "hash": "62a2f64cad5182e1",
  "checksum": "62a2f64cad5182e1",
  "human_score": 4,
  "visual_score": 0.543,
  "tier_max": 4,
  "estimated_time_minutes": 8,
  "tramo": 1,
  "level_index": 169,
  "difficulty_label": "Expert"
}