{
  "id": "expert_0553",
  "puzzle": "093005608500840100008000254010352000062100045957400020780690410001020980000781030",
  "solution": "493215678526847193178936254814352769362179845957468321785693412631524987249781536",
  "difficulty": "expert",
  "clues": 41,
  "fill_percent": 50.6,
  "symmetry": "random",
  "techniques": [
    "LastBlank",
    "FullHouse",
    "NakedSingle",
    "HiddenSingle",
    "PointingPair",
    "PointingTriple",
    "BoxLineReduction",
    "NakedPair",
    "HiddenPair",
    "NakedTriple",
    "HiddenTriple",
    "NakedQuad",
    "HiddenQuad",
    "XWing",
    "XYWing",
    "XYZWing",
    "WWing"
  ],
  "steps": 40,
  "hash": "eace22a711641161",
  "checksum": "eace22a711641161",
  "human_score": 4,
  "visual_score": 0.506,
  "tier_max": 4,
  "estimated_time_minutes": 10,
  "tramo": 401,
  "level_index": 553,
  "difficulty_label": "Expert"
}