{
  "id": "expert_0983",
  "puzzle": "001069205602030084000724300753601042400080513000003090000018600280000109000902030",
  "solution": "341869275672135984895724361753691842469287513128453796934518627287346159516972438",
  "difficulty": "expert",
  "clues": 38,
  "fill_percent": 46.9,
  "symmetry": "random",
  "techniques": [
    "LastBlank",
    "FullHouse",
    "NakedSingle",
    "HiddenSingle",
    "PointingPair",
    "PointingTriple",
    "BoxLineReduction",
    "NakedPair",
    "HiddenPair",
    "NakedTriple",
    "HiddenTriple",
    "NakedQuad",
    "HiddenQuad",
    "XWing",
    "XYWing",
    "XYZWing",
    "WWing",
    "Swordfish",
    "Jellyfish",
    "WXYZWing"
  ],
  "steps": 43,
  "hash": "8702c080249bff05",
  "checksum": "8702c080249bff05",
  "human_score": 5,
  "visual_score": 0.469,
  "tier_max": 5,
  "estimated_time_minutes": 14,
  "tramo": 801,
  "level_index": 983,
  "difficulty_label": "Expert"
}