{
  "id": "expert_0646",
  "puzzle": "600307049070006001248010030001004206860209013403100700030040972100600050780503004",
  "solution": "615327849379486521248915637951734286867259413423168795536841972194672358782593164",
  "difficulty": "expert",
  "clues": 40,
  "fill_percent": 49.4,
  "symmetry": "rotational",
  "techniques": [
    "LastBlank",
    "FullHouse",
    "NakedSingle",
    "HiddenSingle",
    "PointingPair",
    "PointingTriple",
    "BoxLineReduction",
    "NakedPair",
    "HiddenPair",
    "NakedTriple",
    "HiddenTriple",
    "NakedQuad",
    "HiddenQuad",
    "XWing",
    "XYWing",
    "XYZWing",
    "WWing",
    "Swordfish"
  ],
  "steps": 41,
  "hash": "5d2c2d07676e5595",
  "checksum": "5d2c2d07676e5595",
  "human_score": 5,
  "visual_score": 0.494,
  "tier_max": 5,
  "estimated_time_minutes": 12,
  "tramo": 601,
  "level_index": 646,
  "difficulty_label": "Expert"
}