{
  "id": "expert_0811",
  "puzzle": "807241506496300821010090704200800100650000200300000007700100400900402010140503072",
  "solution": "837241596496357821512698734274836159659714283381925647723189465965472318148563972",
  "difficulty": "expert",
  "clues": 39,
  "fill_percent": 48.1,
  "symmetry": "random",
  "techniques": [
    "LastBlank",
    "FullHouse",
    "NakedSingle",
    "HiddenSingle",
    "PointingPair",
    "PointingTriple",
    "BoxLineReduction",
    "NakedPair",
    "HiddenPair",
    "NakedTriple",
    "HiddenTriple",
    "NakedQuad",
    "HiddenQuad",
    "XWing",
    "XYWing",
    "XYZWing",
    "WWing",
    "Swordfish",
    "Jellyfish",
    "WXYZWing"
  ],
  "steps": 42,
  "hash": "a3b39a4b8cea87d5",
  "checksum": "a3b39a4b8cea87d5",
  "human_score": 5,
  "visual_score": 0.481,
  "tier_max": 5,
  "estimated_time_minutes": 14,
  "tramo": 801,
  "level_index": 811,
  "difficulty_label": "Expert"
}