{
  "id": "expert_0301",
  "puzzle": "000067280000084951850390006480005007017406890500700064300052019125640000098170000",
  "solution": "941567283763284951852391476486915327217436895539728164374852619125649738698173542",
  "difficulty": "expert",
  "clues": 42,
  "fill_percent": 51.9,
  "symmetry": "rotational",
  "techniques": [
    "LastBlank",
    "FullHouse",
    "NakedSingle",
    "HiddenSingle",
    "PointingPair",
    "PointingTriple",
    "BoxLineReduction",
    "NakedPair",
    "HiddenPair",
    "NakedTriple",
    "HiddenTriple",
    "NakedQuad",
    "HiddenQuad",
    "XWing",
    "XYWing"
  ],
  "steps": 39,
  "hash": "767051e2984e1215",
  "checksum": "767051e2984e1215",
  "human_score": 4,
  "visual_score": 0.519,
  "tier_max": 4,
  "estimated_time_minutes": 9,
  "tramo": 201,
  "level_index": 301,
  "difficulty_label": "Expert"
}