{
  "id": "expert_0809",
  "puzzle": "409702000528309000006508000057001430003070109040000057090056273102800004300920810",
  "solution": "419762385528349761736518942257691438683475129941283657894156273162837594375924816",
  "difficulty": "expert",
  "clues": 39,
  "fill_percent": 48.1,
  "symmetry": "random",
  "techniques": [
    "LastBlank",
    "FullHouse",
    "NakedSingle",
    "HiddenSingle",
    "PointingPair",
    "PointingTriple",
    "BoxLineReduction",
    "NakedPair",
    "HiddenPair",
    "NakedTriple",
    "HiddenTriple",
    "NakedQuad",
    "HiddenQuad",
    "XWing",
    "XYWing",
    "XYZWing",
    "WWing",
    "Swordfish",
    "Jellyfish",
    "WXYZWing"
  ],
  "steps": 42,
  "hash": "01f5e483255bc6ea",
  "checksum": "01f5e483255bc6ea",
  "human_score": 5,
  "visual_score": 0.481,
  "tier_max": 5,
  "estimated_time_minutes": 14,
  "tramo": 801,
  "level_index": 809,
  "difficulty_label": "Expert"
}